omnipresense/__init__.py
omnipresense/radar.py
omnipresense-0.2.0.dist-info/METADATA
omnipresense-0.2.0.dist-info/WHEEL
omnipresense-0.2.0.dist-info/RECORD
