Metadata-Version: 2.4
Name: omnipresense
Version: 0.2.0
Summary: A comprehensive, type-safe Python interface for OmniPreSense radar sensors
Project-URL: Homepage, https://github.com/graeb/OmnipresenseRadar
Project-URL: Documentation, https://github.com/graeb/OmnipresenseRadar
Project-URL: Repository, https://github.com/graeb/OmnipresenseRadar.git
Project-URL: Issues, https://github.com/graeb/OmnipresenseRadar/issues
Author-email: Oskar Graeb <graeb.oskar@gmail.com>
License: MIT
Keywords: doppler,fmcw,omnipresense,radar,sensor
Classifier: Development Status :: 3 - Alpha
Classifier: Intended Audience :: Developers
Classifier: License :: OSI Approved :: MIT License
Classifier: Programming Language :: Python :: 3
Classifier: Programming Language :: Python :: 3.8
Classifier: Programming Language :: Python :: 3.9
Classifier: Programming Language :: Python :: 3.10
Classifier: Programming Language :: Python :: 3.11
Classifier: Programming Language :: Python :: 3.12
Classifier: Topic :: Scientific/Engineering
Classifier: Topic :: System :: Hardware :: Hardware Drivers
Requires-Python: >=3.8.1
Requires-Dist: pyserial>=3.4
Provides-Extra: dev
Requires-Dist: autoflake>=2.0.0; extra == 'dev'
Requires-Dist: bandit[toml]>=1.7.0; extra == 'dev'
Requires-Dist: black>=24.0.0; extra == 'dev'
Requires-Dist: isort>=5.13.0; extra == 'dev'
Requires-Dist: mypy>=1.11.0; extra == 'dev'
Requires-Dist: pre-commit>=3.0.0; extra == 'dev'
Requires-Dist: pydocstyle>=6.3.0; extra == 'dev'
Requires-Dist: pytest-cov>=5.0.0; extra == 'dev'
Requires-Dist: pytest-mock>=3.14.0; extra == 'dev'
Requires-Dist: pytest>=8.0.0; extra == 'dev'
Requires-Dist: pyupgrade>=3.8.0; extra == 'dev'
Requires-Dist: ruff>=0.6.0; extra == 'dev'
Requires-Dist: safety>=3.0.0; extra == 'dev'
Requires-Dist: types-pyserial>=3.4.0; extra == 'dev'
